odoo/addons/auth_oidc_environment/README.rst
odoo/addons/auth_oidc_environment/__init__.py
odoo/addons/auth_oidc_environment/__manifest__.py
odoo/addons/auth_oidc_environment/i18n/auth_oidc_environment.pot
odoo/addons/auth_oidc_environment/models/__init__.py
odoo/addons/auth_oidc_environment/models/auth_oauth_provider.py
odoo/addons/auth_oidc_environment/readme/CONFIGURE.rst
odoo/addons/auth_oidc_environment/readme/CONTRIBUTORS.rst
odoo/addons/auth_oidc_environment/readme/DESCRIPTION.rst
odoo/addons/auth_oidc_environment/readme/USAGE.rst
odoo/addons/auth_oidc_environment/static/description/icon.png
odoo/addons/auth_oidc_environment/static/description/index.html
odoo/addons/auth_oidc_environment/tests/__init__.py
odoo/addons/auth_oidc_environment/tests/test_auth_oidc_environment.py
odoo14_addon_auth_oidc_environment-14.0.1.0.1.dist-info/METADATA
odoo14_addon_auth_oidc_environment-14.0.1.0.1.dist-info/WHEEL
odoo14_addon_auth_oidc_environment-14.0.1.0.1.dist-info/top_level.txt
odoo14_addon_auth_oidc_environment-14.0.1.0.1.dist-info/RECORD
