Metadata-Version: 2.1
Name: odoo14-addon-auth-oidc-environment
Version: 14.0.1.0.1
Summary: This module allows to use server env for OIDC configuration
Home-page: https://github.com/OCA/server-auth
Author: ACSONE SA/NV,Odoo Community Association (OCA)
Author-email: support@odoo-community.org
License: AGPL-3
Platform: UNKNOWN
Classifier: Programming Language :: Python
Classifier: Framework :: Odoo
Classifier: Framework :: Odoo :: 14.0
Classifier: License :: OSI Approved :: GNU Affero General Public License v3
Requires-Python: >=3.6
Requires-Dist: odoo14-addon-auth-oidc
Requires-Dist: odoo14-addon-server-environment
Requires-Dist: odoo <14.1dev,>=14.0a
